factoriohelper/README.md
factoriohelper/example-recipes.txt
factoriohelper/example-recipes.txt.license
factoriohelper/graphs.py
factoriohelper/gui.py
factoriohelper/planner.py
factoriohelper/LICENSES/GPL-2.0-only.txt
factoriohelper-1.2.0.dist-info/METADATA
factoriohelper-1.2.0.dist-info/WHEEL
factoriohelper-1.2.0.dist-info/entry_points.txt
factoriohelper-1.2.0.dist-info/RECORD
