Metadata-Version: 2.1
Name: factoriohelper
Version: 1.2.0
Summary: A small application that helps playing factorio more efficiently.
Project-URL: Homepage, https://gitlab.com/AnthonyZimmermann/factoriohelper
Project-URL: Sources, https://gitlab.com/AnthonyZimmermann/factoriohelper
Author-email: Anthony Zimmermann <anthony.zimmermann@protonmail.com>
Keywords: calculate,calculator,factorio,plan,planning,recipe,recipes
Classifier: Development Status :: 3 - Alpha
Classifier: Intended Audience :: Developers
Classifier: Intended Audience :: End Users/Desktop
Classifier: License :: OSI Approved :: GNU General Public License v2 (GPLv2)
Classifier: Natural Language :: English
Classifier: Operating System :: MacOS :: MacOS X
Classifier: Operating System :: Microsoft
Classifier: Operating System :: Microsoft :: Windows
Classifier: Operating System :: POSIX
Classifier: Operating System :: POSIX :: Linux
Classifier: Programming Language :: Python
Classifier: Programming Language :: Python :: 3
Classifier: Programming Language :: Python :: 3 :: Only
Classifier: Programming Language :: Python :: 3.11
Classifier: Programming Language :: Python :: 3.12
Classifier: Programming Language :: Python :: 3.13
Classifier: Topic :: Multimedia
Classifier: Topic :: Multimedia :: Graphics :: Presentation
Classifier: Topic :: Multimedia :: Graphics :: Viewers
Classifier: Topic :: Scientific/Engineering
Classifier: Topic :: Scientific/Engineering :: Information Analysis
Classifier: Topic :: Scientific/Engineering :: Visualization
Classifier: Topic :: Utilities
Requires-Python: >=3.11
Requires-Dist: appdirs<2.0.0,>=1.4.4
Requires-Dist: matplotlib<4.0.0,>=3.8.2
Requires-Dist: networkx<4.0.0,>=3.2.1
Requires-Dist: pygraphviz<2.0,>=1.11
